pysecretary/__init__.py
pysecretary/exceptions.py
pysecretary/gcp.py
pysecretary/prefix.py
pysecretary/pysecretary.py
pysecretary/registry.py
pysecretary/retriever.py
pysecretary-0.1.5.dist-info/AUTHORS.rst
pysecretary-0.1.5.dist-info/LICENSE
pysecretary-0.1.5.dist-info/METADATA
pysecretary-0.1.5.dist-info/WHEEL
pysecretary-0.1.5.dist-info/top_level.txt
pysecretary-0.1.5.dist-info/RECORD
