Metadata-Version: 2.1
Name: pysecretary
Version: 0.1.5
Summary: PySecretary is a python secrets library
Home-page: https://github.com/spennymac/pysecretary
Author: Spencer McCreary
Author-email: spencer_mccreary@compulsivesoftware.com
License: MIT license
Keywords: pysecretary
Platform: UNKNOWN
Classifier: Development Status :: 2 - Pre-Alpha
Classifier: Intended Audience :: Developers
Classifier: License :: OSI Approved :: MIT License
Classifier: Natural Language :: English
Classifier: Programming Language :: Python :: 3
Classifier: Programming Language :: Python :: 3.5
Classifier: Programming Language :: Python :: 3.6
Classifier: Programming Language :: Python :: 3.7
Classifier: Programming Language :: Python :: 3.8
Requires-Python: >=3.5
